Nova/__init__.py
Nova/Core/ServerBase.py
Nova/Core/Stream.py
Nova/Server/Defines.py
Nova/Server/Http.py
Nova_EveFamilia-0.4.2.dist-info/LICENSE
Nova_EveFamilia-0.4.2.dist-info/METADATA
Nova_EveFamilia-0.4.2.dist-info/WHEEL
Nova_EveFamilia-0.4.2.dist-info/top_level.txt
Nova_EveFamilia-0.4.2.dist-info/RECORD
