Metadata-Version: 2.1
Name: Nova-EveFamilia
Version: 0.4.2
Summary: WebApplication Framework
Home-page: https://github.com/Eve-Familia-Inc/Nova
Author: Eve.Familia, Inc.
Author-email: eve@eve.ninja
License: UNKNOWN
Project-URL: Documentation, https://nova.eve.ninja/
Project-URL: Homepage, https://nova.eve.ninja/
Project-URL: Source, https://github.com/Eve-Familia-Inc/Nova
Platform: UNKNOWN
Classifier: Development Status :: 4 - Beta
Classifier: Environment :: Web Environment
Classifier: Programming Language :: Python :: 3.9
Classifier: Intended Audience :: Developers
Classifier: License :: OSI Approved :: MIT License
Classifier: Natural Language :: Japanese
Classifier: Operating System :: OS Independent
Classifier: Topic :: Internet :: WWW/HTTP :: HTTP Servers
Requires-Python: >=3.7
Requires-Dist: brotli
